vpxhw_db_job_locator/__init__.py
vpxhw_db_job_locator/dashboard_url.py
vpxhw_db_job_locator/job_id_gen.py
vpxhw_db_job_locator/test/__init__.py
vpxhw_db_job_locator/test/dashboard_url_test.py
vpxhw_db_job_locator/test/job_id_gen_test.py
vpxhw_db_job_locator-2.7.dist-info/DESCRIPTION.rst
vpxhw_db_job_locator-2.7.dist-info/METADATA
vpxhw_db_job_locator-2.7.dist-info/RECORD
vpxhw_db_job_locator-2.7.dist-info/WHEEL
vpxhw_db_job_locator-2.7.dist-info/metadata.json
vpxhw_db_job_locator-2.7.dist-info/top_level.txt
