Metadata-Version: 2.0
Name: vpxhw-db-job-locator
Version: 2.7
Summary: package for locating jobs in vpxhw database
Home-page: UNKNOWN
Author: Ray Xu
Author-email: rxuniverse@google.com
License: UNKNOWN
Platform: UNKNOWN
Classifier: Programming Language :: Python :: 2
Classifier: License :: OSI Approved :: MIT License
Classifier: Operating System :: OS Independent
Requires-Dist: Jinja2
Requires-Dist: pandas-gbq
Requires-Dist: requests (>=2.20.1)
